CHANGELOG.txt
LICENCE.txt
MANIFEST.in
README.md
setup.py
myjdb/__init__.py
myjdb/myjdb.py
myjdb.egg-info/PKG-INFO
myjdb.egg-info/SOURCES.txt
myjdb.egg-info/dependency_links.txt
myjdb.egg-info/requires.txt
myjdb.egg-info/top_level.txt