Metadata-Version: 2.1
Name: myjdb
Version: 0.0.2
Summary: A simple and lightweight JSON mock database for small projects
Home-page: 
Author: Abhay S Prasad (KingCosma)
Author-email: abhaygorur@gmail.com
License: MIT
Keywords: calculator
Classifier: Development Status :: 5 - Production/Stable
Classifier: Intended Audience :: Education
Classifier: Operating System :: Microsoft :: Windows :: Windows 10
Classifier: License :: OSI Approved :: MIT License
Classifier: Programming Language :: Python :: 3
License-File: LICENCE.txt
Requires-Dist: json
Requires-Dist: collections.abc
Requires-Dist: random
Requires-Dist: string
